README.md
setup.py
cheesefactory_postgres/__init__.py
cheesefactory_postgres.egg-info/PKG-INFO
cheesefactory_postgres.egg-info/SOURCES.txt
cheesefactory_postgres.egg-info/dependency_links.txt
cheesefactory_postgres.egg-info/requires.txt
cheesefactory_postgres.egg-info/top_level.txt