Metadata-Version: 2.1
Name: cheesefactory-postgres
Version: 0.1
Summary: A simple PostgreSQL wrapper for psycopg2.
Home-page: https://bitbucket.org/hellsgrannies/cheesefactory-postgres
Author: Todd Salazar
Author-email: unixsal@yahoo.com
License: UNKNOWN
Keywords: cheesefactory psycopg2 postgres postgresql development
Platform: UNKNOWN
Classifier: Development Status :: 4 - Beta
Classifier: Intended Audience :: Developers
Classifier: License :: OSI Approved :: BSD License
Classifier: Programming Language :: Python :: 3.6
Classifier: Programming Language :: Python :: 3.7
Classifier: Programming Language :: Python :: 3.8
